my_classes/__init__.py
my_classes/person.py
my_classes/student.py
my_classes/teacher.py
my_classes-0.0.5.dist-info/METADATA
my_classes-0.0.5.dist-info/WHEEL
my_classes-0.0.5.dist-info/top_level.txt
my_classes-0.0.5.dist-info/RECORD
