Metadata-Version: 2.1
Name: my-classes
Version: 0.0.5
Summary: classes
Home-page: https://gitlab.com/netstack_course/my-package/-/tree/develop
Author: Kamilsh323
Author-email: kamilsh323@gmail.com
Classifier: Programming Language :: Python :: 3
Classifier: License :: OSI Approved :: MIT License
Classifier: Operating System :: OS Independent
Requires-Python: >=3.6
